{
  "all": {
    "1": {
      "current": 66,
      "max": 66,
      "history": [],
      "appearances": 37,
      "avgInterval": 14.3,
      "dueScore": 461.6
    },
    "2": {
      "current": 18,
      "max": 58,
      "history": [],
      "appearances": 40,
      "avgInterval": 13.22,
      "dueScore": 136.1
    },
    "3": {
      "current": 16,
      "max": 40,
      "history": [],
      "appearances": 39,
      "avgInterval": 13.56,
      "dueScore": 118
    },
    "4": {
      "current": 44,
      "max": 44,
      "history": [],
      "appearances": 47,
      "avgInterval": 11.26,
      "dueScore": 390.9
    },
    "5": {
      "current": 30,
      "max": 61,
      "history": [],
      "appearances": 39,
      "avgInterval": 13.56,
      "dueScore": 221.2
    },
    "6": {
      "current": 6,
      "max": 67,
      "history": [],
      "appearances": 39,
      "avgInterval": 13.56,
      "dueScore": 44.2
    },
    "7": {
      "current": 74,
      "max": 79,
      "history": [],
      "appearances": 32,
      "avgInterval": 16.53,
      "dueScore": 447.6
    },
    "8": {
      "current": 16,
      "max": 63,
      "history": [],
      "appearances": 35,
      "avgInterval": 15.11,
      "dueScore": 105.9
    },
    "9": {
      "current": 0,
      "max": 81,
      "history": [],
      "appearances": 40,
      "avgInterval": 13.22,
      "dueScore": 0
    },
    "10": {
      "current": 68,
      "max": 68,
      "history": [],
      "appearances": 23,
      "avgInterval": 23,
      "dueScore": 295.7
    },
    "11": {
      "current": 27,
      "max": 48,
      "history": [],
      "appearances": 45,
      "avgInterval": 11.76,
      "dueScore": 229.7
    },
    "12": {
      "current": 79,
      "max": 79,
      "history": [],
      "appearances": 42,
      "avgInterval": 12.6,
      "dueScore": 627.2
    },
    "13": {
      "current": 70,
      "max": 70,
      "history": [],
      "appearances": 24,
      "avgInterval": 22.04,
      "dueScore": 317.6
    },
    "14": {
      "current": 18,
      "max": 73,
      "history": [],
      "appearances": 26,
      "avgInterval": 20.35,
      "dueScore": 88.5
    },
    "15": {
      "current": 41,
      "max": 60,
      "history": [],
      "appearances": 33,
      "avgInterval": 16.03,
      "dueScore": 255.8
    },
    "16": {
      "current": 2,
      "max": 41,
      "history": [],
      "appearances": 41,
      "avgInterval": 12.9,
      "dueScore": 15.5
    },
    "17": {
      "current": 83,
      "max": 83,
      "history": [],
      "appearances": 29,
      "avgInterval": 18.24,
      "dueScore": 455
    },
    "18": {
      "current": 2,
      "max": 40,
      "history": [],
      "appearances": 42,
      "avgInterval": 12.6,
      "dueScore": 15.9
    },
    "19": {
      "current": 2,
      "max": 62,
      "history": [],
      "appearances": 44,
      "avgInterval": 12.02,
      "dueScore": 16.6
    },
    "20": {
      "current": 6,
      "max": 65,
      "history": [],
      "appearances": 33,
      "avgInterval": 16.03,
      "dueScore": 37.4
    },
    "21": {
      "current": 20,
      "max": 80,
      "history": [],
      "appearances": 51,
      "avgInterval": 10.37,
      "dueScore": 192.8
    },
    "22": {
      "current": 9,
      "max": 62,
      "history": [],
      "appearances": 29,
      "avgInterval": 18.24,
      "dueScore": 49.3
    },
    "23": {
      "current": 4,
      "max": 70,
      "history": [],
      "appearances": 45,
      "avgInterval": 11.76,
      "dueScore": 34
    },
    "24": {
      "current": 34,
      "max": 40,
      "history": [],
      "appearances": 49,
      "avgInterval": 10.8,
      "dueScore": 314.9
    },
    "25": {
      "current": 11,
      "max": 50,
      "history": [],
      "appearances": 36,
      "avgInterval": 14.69,
      "dueScore": 74.9
    },
    "26": {
      "current": 27,
      "max": 56,
      "history": [],
      "appearances": 35,
      "avgInterval": 15.11,
      "dueScore": 178.6
    },
    "27": {
      "current": 13,
      "max": 52,
      "history": [],
      "appearances": 53,
      "avgInterval": 9.98,
      "dueScore": 130.2
    },
    "28": {
      "current": 9,
      "max": 45,
      "history": [],
      "appearances": 53,
      "avgInterval": 9.98,
      "dueScore": 90.2
    },
    "29": {
      "current": 13,
      "max": 52,
      "history": [],
      "appearances": 36,
      "avgInterval": 14.69,
      "dueScore": 88.5
    },
    "30": {
      "current": 13,
      "max": 57,
      "history": [],
      "appearances": 36,
      "avgInterval": 14.69,
      "dueScore": 88.5
    },
    "31": {
      "current": 16,
      "max": 61,
      "history": [],
      "appearances": 46,
      "avgInterval": 11.5,
      "dueScore": 139.1
    },
    "32": {
      "current": 69,
      "max": 69,
      "history": [],
      "appearances": 34,
      "avgInterval": 15.56,
      "dueScore": 443.5
    },
    "33": {
      "current": 0,
      "max": 53,
      "history": [],
      "appearances": 53,
      "avgInterval": 9.98,
      "dueScore": 0
    },
    "34": {
      "current": 30,
      "max": 37,
      "history": [],
      "appearances": 39,
      "avgInterval": 13.56,
      "dueScore": 221.2
    },
    "35": {
      "current": 20,
      "max": 58,
      "history": [],
      "appearances": 43,
      "avgInterval": 12.3,
      "dueScore": 162.6
    },
    "36": {
      "current": 11,
      "max": 72,
      "history": [],
      "appearances": 37,
      "avgInterval": 14.3,
      "dueScore": 76.9
    },
    "37": {
      "current": 13,
      "max": 57,
      "history": [],
      "appearances": 39,
      "avgInterval": 13.56,
      "dueScore": 95.8
    },
    "38": {
      "current": 48,
      "max": 59,
      "history": [],
      "appearances": 36,
      "avgInterval": 14.69,
      "dueScore": 326.7
    },
    "39": {
      "current": 34,
      "max": 71,
      "history": [],
      "appearances": 39,
      "avgInterval": 13.56,
      "dueScore": 250.7
    },
    "40": {
      "current": 6,
      "max": 61,
      "history": [],
      "appearances": 43,
      "avgInterval": 12.3,
      "dueScore": 48.8
    },
    "41": {
      "current": 58,
      "max": 66,
      "history": [],
      "appearances": 23,
      "avgInterval": 23,
      "dueScore": 252.2
    },
    "42": {
      "current": 11,
      "max": 89,
      "history": [],
      "appearances": 31,
      "avgInterval": 17.06,
      "dueScore": 64.5
    },
    "43": {
      "current": 4,
      "max": 43,
      "history": [],
      "appearances": 47,
      "avgInterval": 11.26,
      "dueScore": 35.5
    },
    "44": {
      "current": 70,
      "max": 70,
      "history": [],
      "appearances": 41,
      "avgInterval": 12.9,
      "dueScore": 542.5
    },
    "45": {
      "current": 37,
      "max": 62,
      "history": [],
      "appearances": 38,
      "avgInterval": 13.92,
      "dueScore": 265.8
    },
    "46": {
      "current": 20,
      "max": 66,
      "history": [],
      "appearances": 32,
      "avgInterval": 16.53,
      "dueScore": 121
    },
    "47": {
      "current": 72,
      "max": 72,
      "history": [],
      "appearances": 40,
      "avgInterval": 13.22,
      "dueScore": 544.4
    },
    "48": {
      "current": 6,
      "max": 55,
      "history": [],
      "appearances": 34,
      "avgInterval": 15.56,
      "dueScore": 38.6
    },
    "49": {
      "current": 32,
      "max": 70,
      "history": [],
      "appearances": 29,
      "avgInterval": 18.24,
      "dueScore": 175.4
    },
    "50": {
      "current": 78,
      "max": 78,
      "history": [],
      "appearances": 33,
      "avgInterval": 16.03,
      "dueScore": 486.6
    },
    "51": {
      "current": 11,
      "max": 34,
      "history": [],
      "appearances": 39,
      "avgInterval": 13.56,
      "dueScore": 81.1
    },
    "52": {
      "current": 0,
      "max": 53,
      "history": [],
      "appearances": 45,
      "avgInterval": 11.76,
      "dueScore": 0
    },
    "53": {
      "current": 27,
      "max": 30,
      "history": [],
      "appearances": 46,
      "avgInterval": 11.5,
      "dueScore": 234.8
    },
    "54": {
      "current": 58,
      "max": 60,
      "history": [],
      "appearances": 35,
      "avgInterval": 15.11,
      "dueScore": 383.7
    },
    "55": {
      "current": 27,
      "max": 85,
      "history": [],
      "appearances": 30,
      "avgInterval": 17.63,
      "dueScore": 153.1
    },
    "56": {
      "current": 2,
      "max": 82,
      "history": [],
      "appearances": 27,
      "avgInterval": 19.59,
      "dueScore": 10.2
    },
    "57": {
      "current": 32,
      "max": 53,
      "history": [],
      "appearances": 35,
      "avgInterval": 15.11,
      "dueScore": 211.7
    },
    "58": {
      "current": 2,
      "max": 48,
      "history": [],
      "appearances": 46,
      "avgInterval": 11.5,
      "dueScore": 17.4
    },
    "59": {
      "current": 37,
      "max": 73,
      "history": [],
      "appearances": 35,
      "avgInterval": 15.11,
      "dueScore": 244.8
    },
    "60": {
      "current": 4,
      "max": 46,
      "history": [],
      "appearances": 40,
      "avgInterval": 13.22,
      "dueScore": 30.2
    },
    "61": {
      "current": 25,
      "max": 56,
      "history": [],
      "appearances": 39,
      "avgInterval": 13.56,
      "dueScore": 184.3
    },
    "62": {
      "current": 53,
      "max": 62,
      "history": [],
      "appearances": 41,
      "avgInterval": 12.9,
      "dueScore": 410.8
    },
    "63": {
      "current": 18,
      "max": 58,
      "history": [],
      "appearances": 41,
      "avgInterval": 12.9,
      "dueScore": 139.5
    },
    "64": {
      "current": 0,
      "max": 47,
      "history": [],
      "appearances": 49,
      "avgInterval": 10.8,
      "dueScore": 0
    },
    "65": {
      "current": 16,
      "max": 68,
      "history": [],
      "appearances": 28,
      "avgInterval": 18.89,
      "dueScore": 84.7
    },
    "66": {
      "current": 0,
      "max": 60,
      "history": [],
      "appearances": 44,
      "avgInterval": 12.02,
      "dueScore": 0
    },
    "67": {
      "current": 88,
      "max": 88,
      "history": [],
      "appearances": 37,
      "avgInterval": 14.3,
      "dueScore": 615.5
    },
    "68": {
      "current": 20,
      "max": 67,
      "history": [],
      "appearances": 37,
      "avgInterval": 14.3,
      "dueScore": 139.9
    },
    "69": {
      "current": 60,
      "max": 60,
      "history": [],
      "appearances": 41,
      "avgInterval": 12.9,
      "dueScore": 465
    }
  },
  "ranking": [
    {
      "num": 12,
      "current": 79,
      "max": 79,
      "history": [],
      "appearances": 42,
      "avgInterval": 12.6,
      "dueScore": 627.2
    },
    {
      "num": 67,
      "current": 88,
      "max": 88,
      "history": [],
      "appearances": 37,
      "avgInterval": 14.3,
      "dueScore": 615.5
    },
    {
      "num": 47,
      "current": 72,
      "max": 72,
      "history": [],
      "appearances": 40,
      "avgInterval": 13.22,
      "dueScore": 544.4
    },
    {
      "num": 44,
      "current": 70,
      "max": 70,
      "history": [],
      "appearances": 41,
      "avgInterval": 12.9,
      "dueScore": 542.5
    },
    {
      "num": 50,
      "current": 78,
      "max": 78,
      "history": [],
      "appearances": 33,
      "avgInterval": 16.03,
      "dueScore": 486.6
    },
    {
      "num": 69,
      "current": 60,
      "max": 60,
      "history": [],
      "appearances": 41,
      "avgInterval": 12.9,
      "dueScore": 465
    },
    {
      "num": 1,
      "current": 66,
      "max": 66,
      "history": [],
      "appearances": 37,
      "avgInterval": 14.3,
      "dueScore": 461.6
    },
    {
      "num": 17,
      "current": 83,
      "max": 83,
      "history": [],
      "appearances": 29,
      "avgInterval": 18.24,
      "dueScore": 455
    },
    {
      "num": 7,
      "current": 74,
      "max": 79,
      "history": [],
      "appearances": 32,
      "avgInterval": 16.53,
      "dueScore": 447.6
    },
    {
      "num": 32,
      "current": 69,
      "max": 69,
      "history": [],
      "appearances": 34,
      "avgInterval": 15.56,
      "dueScore": 443.5
    },
    {
      "num": 62,
      "current": 53,
      "max": 62,
      "history": [],
      "appearances": 41,
      "avgInterval": 12.9,
      "dueScore": 410.8
    },
    {
      "num": 4,
      "current": 44,
      "max": 44,
      "history": [],
      "appearances": 47,
      "avgInterval": 11.26,
      "dueScore": 390.9
    },
    {
      "num": 54,
      "current": 58,
      "max": 60,
      "history": [],
      "appearances": 35,
      "avgInterval": 15.11,
      "dueScore": 383.7
    },
    {
      "num": 38,
      "current": 48,
      "max": 59,
      "history": [],
      "appearances": 36,
      "avgInterval": 14.69,
      "dueScore": 326.7
    },
    {
      "num": 13,
      "current": 70,
      "max": 70,
      "history": [],
      "appearances": 24,
      "avgInterval": 22.04,
      "dueScore": 317.6
    }
  ]
}