{
  "game": "powerball",
  "drawDate": "2023-06-21",
  "numbers": [
    5,
    11,
    33,
    35,
    63
  ],
  "powerBall": 14,
  "powerPlay": 2,
  "jackpot": {
    "estimated": 401000000,
    "cash": 207400000,
    "winners": 0
  },
  "prizeTiers": [
    {
      "tier": 0,
      "matchWhite": 5,
      "matchSpecial": true,
      "isJackpot": true,
      "winners": {
        "base": 0,
        "multiplier": 0
      },
      "prize": {
        "base": "JACKPOT",
        "multiplier": 0
      },
      "odds": 292201338
    },
    {
      "tier": 1,
      "matchWhite": 5,
      "matchSpecial": false,
      "isJackpot": false,
      "winners": {
        "base": 0,
        "multiplier": 0
      },
      "prize": {
        "base": 1000000,
        "multiplier": 2000000
      },
      "odds": 11688054
    },
    {
      "tier": 2,
      "matchWhite": 4,
      "matchSpecial": true,
      "isJackpot": false,
      "winners": {
        "base": 11,
        "multiplier": 2
      },
      "prize": {
        "base": 50000,
        "multiplier": 100000
      },
      "odds": 913129
    },
    {
      "tier": 3,
      "matchWhite": 4,
      "matchSpecial": false,
      "isJackpot": false,
      "winners": {
        "base": 342,
        "multiplier": 96
      },
      "prize": {
        "base": 100,
        "multiplier": 200
      },
      "odds": 36525
    },
    {
      "tier": 4,
      "matchWhite": 3,
      "matchSpecial": true,
      "isJackpot": false,
      "winners": {
        "base": 817,
        "multiplier": 240
      },
      "prize": {
        "base": 100,
        "multiplier": 200
      },
      "odds": 14494
    },
    {
      "tier": 5,
      "matchWhite": 3,
      "matchSpecial": false,
      "isJackpot": false,
      "winners": {
        "base": 20503,
        "multiplier": 6267
      },
      "prize": {
        "base": 7,
        "multiplier": 14
      },
      "odds": 579
    },
    {
      "tier": 6,
      "matchWhite": 2,
      "matchSpecial": true,
      "isJackpot": false,
      "winners": {
        "base": 16808,
        "multiplier": 5063
      },
      "prize": {
        "base": 7,
        "multiplier": 14
      },
      "odds": 701
    },
    {
      "tier": 7,
      "matchWhite": 1,
      "matchSpecial": true,
      "isJackpot": false,
      "winners": {
        "base": 126395,
        "multiplier": 37885
      },
      "prize": {
        "base": 4,
        "multiplier": 8
      },
      "odds": 92
    },
    {
      "tier": 8,
      "matchWhite": 0,
      "matchSpecial": true,
      "isJackpot": false,
      "winners": {
        "base": 296181,
        "multiplier": 88798
      },
      "prize": {
        "base": 4,
        "multiplier": 8
      },
      "odds": 38
    }
  ],
  "videoCode": "tl3ddZ1d4yc",
  "source": "powerball.com",
  "fetchedAt": "2025-12-15T15:30:37.599Z"
}