{
  "game": "powerball",
  "drawDate": "2026-01-12",
  "numbers": [
    5,
    19,
    21,
    28,
    64
  ],
  "powerBall": 14,
  "powerPlay": 3,
  "jackpot": {
    "estimated": 126000000,
    "cash": 57100000,
    "winners": 0
  },
  "prizeTiers": [
    {
      "tier": 0,
      "matchWhite": 5,
      "matchSpecial": true,
      "isJackpot": true,
      "winners": {
        "base": 0,
        "multiplier": 0
      },
      "prize": {
        "base": "JACKPOT",
        "multiplier": 0
      },
      "odds": 292201338
    },
    {
      "tier": 1,
      "matchWhite": 5,
      "matchSpecial": false,
      "isJackpot": false,
      "winners": {
        "base": 3,
        "multiplier": 0
      },
      "prize": {
        "base": 1000000,
        "multiplier": 2000000
      },
      "odds": 11688054
    },
    {
      "tier": 2,
      "matchWhite": 4,
      "matchSpecial": true,
      "isJackpot": false,
      "winners": {
        "base": 11,
        "multiplier": 4
      },
      "prize": {
        "base": 50000,
        "multiplier": 150000
      },
      "odds": 913129
    },
    {
      "tier": 3,
      "matchWhite": 4,
      "matchSpecial": false,
      "isJackpot": false,
      "winners": {
        "base": 340,
        "multiplier": 127
      },
      "prize": {
        "base": 100,
        "multiplier": 300
      },
      "odds": 36525
    },
    {
      "tier": 4,
      "matchWhite": 3,
      "matchSpecial": true,
      "isJackpot": false,
      "winners": {
        "base": 892,
        "multiplier": 326
      },
      "prize": {
        "base": 100,
        "multiplier": 300
      },
      "odds": 14494
    },
    {
      "tier": 5,
      "matchWhite": 3,
      "matchSpecial": false,
      "isJackpot": false,
      "winners": {
        "base": 22722,
        "multiplier": 7990
      },
      "prize": {
        "base": 7,
        "multiplier": 21
      },
      "odds": 579
    },
    {
      "tier": 6,
      "matchWhite": 2,
      "matchSpecial": true,
      "isJackpot": false,
      "winners": {
        "base": 17153,
        "multiplier": 6039
      },
      "prize": {
        "base": 7,
        "multiplier": 21
      },
      "odds": 701
    },
    {
      "tier": 7,
      "matchWhite": 1,
      "matchSpecial": true,
      "isJackpot": false,
      "winners": {
        "base": 122583,
        "multiplier": 42295
      },
      "prize": {
        "base": 4,
        "multiplier": 12
      },
      "odds": 92
    },
    {
      "tier": 8,
      "matchWhite": 0,
      "matchSpecial": true,
      "isJackpot": false,
      "winners": {
        "base": 277679,
        "multiplier": 93330
      },
      "prize": {
        "base": 4,
        "multiplier": 12
      },
      "odds": 38
    }
  ],
  "winners": [
    {
      "title": "Powerball",
      "description": "JACKPOT WINNERS",
      "locations": "None"
    },
    {
      "title": "Match 5 + Power Play",
      "description": "$2 Million Winners",
      "locations": "None"
    },
    {
      "title": "Match 5",
      "description": "$1 Million Winners",
      "locations": "CA, OH, OR"
    }
  ],
  "videoCode": "4T3rc_LUF9g",
  "source": "powerball.com",
  "fetchedAt": "2026-01-12T07:34:26.143Z"
}